streamlit_product_card/__init__.py
streamlit_product_card/frontend/build/asset-manifest.json
streamlit_product_card/frontend/build/bootstrap.min.css
streamlit_product_card/frontend/build/bootstrap.min.css.map
streamlit_product_card/frontend/build/index.html
streamlit_product_card/frontend/build/precache-manifest.97cef19da26898ae952328e7d12fc44a.js
streamlit_product_card/frontend/build/service-worker.js
streamlit_product_card/frontend/build/static/js/2.c5ccbe22.chunk.js
streamlit_product_card/frontend/build/static/js/2.c5ccbe22.chunk.js.map
streamlit_product_card/frontend/build/static/js/main.091ed07d.chunk.js
streamlit_product_card/frontend/build/static/js/main.091ed07d.chunk.js.map
streamlit_product_card/frontend/build/static/js/runtime~main.d653cc00.js
streamlit_product_card/frontend/build/static/js/runtime~main.d653cc00.js.map
streamlit_product_card-1.0.0.dist-info/licenses/LICENSE
streamlit_product_card-1.0.0.dist-info/METADATA
streamlit_product_card-1.0.0.dist-info/WHEEL
streamlit_product_card-1.0.0.dist-info/top_level.txt
streamlit_product_card-1.0.0.dist-info/RECORD
