Metadata-Version: 2.4
Name: streamlit-product-card
Version: 1.0.0
Summary: An e-commerce product card component for Streamlit
Home-page: https://github.com/msr2903/st-productcard
Author: msr2903
Author-email: michaelpersonal67@gmail.com
Classifier: Programming Language :: Python :: 3
Classifier: License :: OSI Approved :: MIT License
Classifier: Operating System :: OS Independent
Classifier: Topic :: Software Development :: Libraries :: Python Modules
Requires-Python: >=3.8
License-File: LICENSE
Requires-Dist: streamlit>=1.0
Dynamic: author
Dynamic: author-email
Dynamic: classifier
Dynamic: description
Dynamic: description-content-type
Dynamic: home-page
Dynamic: license-file
Dynamic: requires-dist
Dynamic: requires-python
Dynamic: summary
